rdstation/__init__.py
rdstation/client.py
rdstation/crm.py
rdstation/exceptions.py
rdstation_python-0.2.2.dist-info/LICENSE
rdstation_python-0.2.2.dist-info/METADATA
rdstation_python-0.2.2.dist-info/WHEEL
rdstation_python-0.2.2.dist-info/RECORD
