Metadata-Version: 2.1
Name: rdstation-python
Version: 0.2.2
Summary: API wrapper for RD Station written in Python
License: MIT
Author: Juan Carlos Rios
Author-email: juankrios15@gmail.com
Requires-Python: >=3.7,<4.0
Classifier: License :: OSI Approved :: MIT License
Classifier: Programming Language :: Python :: 3
Classifier: Programming Language :: Python :: 3.7
Classifier: Programming Language :: Python :: 3.8
Classifier: Programming Language :: Python :: 3.9
Classifier: Programming Language :: Python :: 3.10
Classifier: Programming Language :: Python :: 3.11
Requires-Dist: requests (>=2.26.0,<3.0.0)
